{
  "users": [
    {
      "id": "1",
      "username": "admin",
      "password": "1234"
    }
  ],
  "tasks": [
    {
      "id": "575d",
      "title": "afasf",
      "desc": "asf",
      "completed": false
    },
    {
      "id": "4d9c",
      "title": "asd",
      "desc": "sad",
      "completed": false
    },
    {
      "id": "d204",
      "title": "asf",
      "desc": "asf",
      "completed": false
    },
    {
      "id": "91f4",
      "title": "asfa",
      "desc": "sf",
      "completed": false
    },
    {
      "id": "bcc8",
      "title": "asd",
      "desc": "asd",
      "completed": false
    }
  ]
}